{
  "Refined Metal": {
    "sell": 9,
    "buy": 9,
    "stock": 9999,
    "craftable": true,
    "isCurrency": true
  },
  "Reclaimed Metal": {
    "sell": 3,
    "buy": 3,
    "stock": 9999,
    "craftable": true,
    "isCurrency": true
  },
  "Scrap Metal": {
    "sell": 1,
    "buy": 1,
    "stock": 9999,
    "craftable": true,
    "isCurrency": true
  },
  "Hat of Cards": {
    "sell": 21,
    "buy": 20,
    "stock": 3,
    "craftable": true
  },
  "Flak Jack": {
    "sell": 62,
    "buy": 61,
    "stock": 3,
    "craftable": true
  },
  "Elf Esteem": {
    "sell": 20,
    "buy": 20,
    "stock": 3,
    "craftable": true
  },
  "El Caballero": {
    "sell": 61,
    "buy": 60,
    "stock": 3,
    "craftable": true
  },
  "The Sky Captain": {
    "sell": 11,
    "buy": 11,
    "stock": 3,
    "craftable": true
  },
  "The Toowoomba Tunic": {
    "sell": 23,
    "buy": 23,
    "stock": 3,
    "craftable": true
  },
  "Trickster's Turnout Gear": {
    "sell": 28,
    "buy": 27,
    "stock": 3,
    "craftable": true
  },
  "Cosa Nostra Cap": {
    "sell": 26,
    "buy": 25,
    "stock": 3,
    "craftable": true
  },
  "Tartan Tyrolean": {
    "sell": 12,
    "buy": 11,
    "stock": 3,
    "craftable": true
  },
  "The Trencher's Tunic": {
    "sell": 24,
    "buy": 23,
    "stock": 3,
    "craftable": true
  }
}